pipoe2/__init__.py
pipoe2/__main__.py
pipoe2-0.1.2.dist-info/METADATA
pipoe2-0.1.2.dist-info/WHEEL
pipoe2-0.1.2.dist-info/entry_points.txt
pipoe2-0.1.2.dist-info/RECORD
