Metadata-Version: 2.1
Name: pipoe2
Version: 0.1.2
Summary: 
Author: mitch mommers
Author-email: mitch.mommers@everythings.be
Requires-Python: >=3.10,<4.0
Classifier: Programming Language :: Python :: 3
Classifier: Programming Language :: Python :: 3.10
Classifier: Programming Language :: Python :: 3.11
Requires-Dist: click (>=8.0.4,<9.0.0)
Requires-Dist: lxml (>=4.9.2,<5.0.0)
Requires-Dist: requests (>=2.28.2,<3.0.0)
Requires-Dist: rich (>=12.3.3,<13.0.0)
